{
  "contest": {
    "id": "abc461",
    "title": "AtCoder Beginner Contest 461",
    "url": "https://atcoder.jp/contests/abc461"
  },
  "tasks": [
    {
      "id": "abc461_a",
      "label": "A",
      "title": "Armor",
      "url": "https://atcoder.jp/contests/abc461/tasks/abc461_a",
      "directory": {
        "path": ".",
        "testdir": "input/a",
        "submit": "maina.py"
      }
    },
    {
      "id": "abc461_b",
      "label": "B",
      "title": "The Honest Woodcutters",
      "url": "https://atcoder.jp/contests/abc461/tasks/abc461_b",
      "directory": {
        "path": ".",
        "testdir": "input/b",
        "submit": "mainb.py"
      }
    },
    {
      "id": "abc461_c",
      "label": "C",
      "title": "Variety",
      "url": "https://atcoder.jp/contests/abc461/tasks/abc461_c",
      "directory": {
        "path": ".",
        "testdir": "input/c",
        "submit": "mainc.py"
      }
    },
    {
      "id": "abc461_d",
      "label": "D",
      "title": "Count Subgrid Sum = K",
      "url": "https://atcoder.jp/contests/abc461/tasks/abc461_d",
      "directory": {
        "path": ".",
        "testdir": "input/d",
        "submit": "maind.py"
      }
    },
    {
      "id": "abc461_e",
      "label": "E",
      "title": "E-liter",
      "url": "https://atcoder.jp/contests/abc461/tasks/abc461_e",
      "directory": {
        "path": ".",
        "testdir": "input/e",
        "submit": "maine.py"
      }
    },
    {
      "id": "abc461_f",
      "label": "F",
      "title": "Total Product is N",
      "url": "https://atcoder.jp/contests/abc461/tasks/abc461_f",
      "directory": {
        "path": ".",
        "testdir": "input/f",
        "submit": "mainf.py"
      }
    },
    {
      "id": "abc461_g",
      "label": "G",
      "title": "Graph Problem 2026",
      "url": "https://atcoder.jp/contests/abc461/tasks/abc461_g",
      "directory": {
        "path": ".",
        "testdir": "input/g",
        "submit": "maing.py"
      }
    }
  ]
}